CHANGELOG.txt
LICENCE.txt
MANIFEST.in
README.txt
setup.py
cisco/__init__.py
cisco.egg-info/PKG-INFO
cisco.egg-info/SOURCES.txt
cisco.egg-info/dependency_links.txt
cisco.egg-info/top_level.txt